openbb_federal_reserve/__init__.py
openbb_federal_reserve/assets/__init__.py
openbb_federal_reserve/assets/historical_releases.json
openbb_federal_reserve/models/central_bank_holdings.py
openbb_federal_reserve/models/federal_funds_rate.py
openbb_federal_reserve/models/fomc_documents.py
openbb_federal_reserve/models/money_measures.py
openbb_federal_reserve/models/overnight_bank_funding_rate.py
openbb_federal_reserve/models/primary_dealer_fails.py
openbb_federal_reserve/models/primary_dealer_positioning.py
openbb_federal_reserve/models/sofr.py
openbb_federal_reserve/models/treasury_rates.py
openbb_federal_reserve/models/yield_curve.py
openbb_federal_reserve/utils/__init__.py
openbb_federal_reserve/utils/fomc_documents.py
openbb_federal_reserve/utils/ny_fed_api.py
openbb_federal_reserve/utils/primary_dealer_statistics.py
openbb_federal_reserve-1.4.3.dist-info/METADATA
openbb_federal_reserve-1.4.3.dist-info/WHEEL
openbb_federal_reserve-1.4.3.dist-info/entry_points.txt
openbb_federal_reserve-1.4.3.dist-info/RECORD
