Metadata-Version: 2.3
Name: openbb-federal-reserve
Version: 1.4.3
Summary: US Federal Reserve Data Extension for OpenBB
License: AGPL-3.0-only
Author: OpenBB
Author-email: hello@openbb.co
Requires-Python: >=3.9.21,<3.13
Classifier: License :: OSI Approved :: GNU Affero General Public License v3
Classifier: Programming Language :: Python :: 3
Classifier: Programming Language :: Python :: 3.10
Classifier: Programming Language :: Python :: 3.11
Classifier: Programming Language :: Python :: 3.12
Requires-Dist: beautifulsoup4 (>=4.13.4,<5.0.0)
Requires-Dist: openbb-core (>=1.4.7,<2.0.0)
